finanzas_personales/__init__.py
finanzas_personales/clearConsole.py
finanzas_personales/database.py
finanzas_personales/graphics.py
finanzas_personales/interface.py
finanzas_personales/main.py
finanzas_personales/models.py
finanzas_personales-0.1.2.dist-info/LICENSE
finanzas_personales-0.1.2.dist-info/METADATA
finanzas_personales-0.1.2.dist-info/WHEEL
finanzas_personales-0.1.2.dist-info/entry_points.txt
finanzas_personales-0.1.2.dist-info/top_level.txt
finanzas_personales-0.1.2.dist-info/RECORD
